cognite/extractorutils/rest/__init__.py
cognite/extractorutils/rest/authentiaction.py
cognite/extractorutils/rest/extractor.py
cognite/extractorutils/rest/http.py
cognite/extractorutils/rest/py.typed
cognite_extractor_utils_rest-0.5.0.dist-info/METADATA
cognite_extractor_utils_rest-0.5.0.dist-info/WHEEL
cognite_extractor_utils_rest-0.5.0.dist-info/LICENSE
cognite_extractor_utils_rest-0.5.0.dist-info/RECORD
