Metadata-Version: 2.1
Name: cognite-extractor-utils-rest
Version: 0.5.0
Summary: REST extention for the Cognite extractor-utils framework
Home-page: https://github.com/cognitedata/python-extractor-utils-rest
License: Apache-2.0
Author: Mathias Lohne
Author-email: mathias.lohne@cognite.com
Requires-Python: >=3.8,<3.11
Classifier: License :: OSI Approved :: Apache Software License
Classifier: Programming Language :: Python :: 3
Classifier: Programming Language :: Python :: 3.8
Classifier: Programming Language :: Python :: 3.9
Classifier: Programming Language :: Python :: 3.10
Requires-Dist: cognite-extractor-utils (>=3.0.2,<4.0.0)
Requires-Dist: requests (>=2.27.0,<3.0.0)
Project-URL: Repository, https://github.com/cognitedata/python-extractor-utils-rest
